invenio_ext/__init__.py
invenio_ext/confighacks.py
invenio_ext/es.py
invenio_ext/menu.py
invenio_ext/version.py
invenio_ext/admin/__init__.py
invenio_ext/admin/views.py
invenio_ext/arxiv/__init__.py
invenio_ext/assets/__init__.py
invenio_ext/assets/commands.py
invenio_ext/assets/extensions.py
invenio_ext/assets/filter.py
invenio_ext/assets/registry.py
invenio_ext/assets/wrappers.py
invenio_ext/babel/__init__.py
invenio_ext/babel/errors.py
invenio_ext/babel/filters.py
invenio_ext/babel/selectors.py
invenio_ext/cache/__init__.py
invenio_ext/collect/__init__.py
invenio_ext/collect/storage/__init__.py
invenio_ext/collect/storage/link.py
invenio_ext/crossref/__init__.py
invenio_ext/debug_toolbar/__init__.py
invenio_ext/email/__init__.py
invenio_ext/email/errors.py
invenio_ext/email/backends/__init__.py
invenio_ext/email/backends/console_adminonly.py
invenio_ext/email/backends/smtp_adminonly.py
invenio_ext/fixtures/__init__.py
invenio_ext/fixtures/registry.py
invenio_ext/fs/__init__.py
invenio_ext/fs/cloudfs/__init__.py
invenio_ext/fs/cloudfs/dropboxfs.py
invenio_ext/fs/cloudfs/googledrivefs.py
invenio_ext/fs/cloudfs/onedrivefs.py
invenio_ext/gravatar/__init__.py
invenio_ext/iiif/__init__.py
invenio_ext/iiif/utils.py
invenio_ext/jasmine/__init__.py
invenio_ext/jasmine/bundles.py
invenio_ext/jasmine/registry.py
invenio_ext/jasmine/views.py
invenio_ext/jasmine/static/js/jasmine/boot.js
invenio_ext/jasmine/static/js/jasmine/events_checker.js
invenio_ext/jasmine/static/js/jasmine/init.js
invenio_ext/jasmine/static/js/jasmine/initialization_checker.js
invenio_ext/jasmine/templates/jasmine/specrunner.html
invenio_ext/jasmine/templates/jasmine/specrunner_base.html
invenio_ext/jasmine/testsuite/__init__.py
invenio_ext/jasmine/testsuite/js/events_checker.spec.js
invenio_ext/jasmine/testsuite/js/initialization_checker.spec.js
invenio_ext/jasmine/testsuite/js/jasmine_configuration.spec.js
invenio_ext-0.3.2.dist-info/top_level.txt
invenio_ext-0.3.2.dist-info/METADATA
invenio_ext-0.3.2.dist-info/DESCRIPTION.rst
invenio_ext-0.3.2.dist-info/metadata.json
invenio_ext-0.3.2.dist-info/WHEEL
invenio_ext-0.3.2.dist-info/RECORD
