Metadata-Version: 2.0
Name: invenio-ext
Version: 0.3.2
Summary: Invenio module that provides integration with Flask extensions.
Home-page: https://github.com/inveniosoftware/invenio-ext
Author: CERN
Author-email: info@invenio-software.org
License: GPLv2
Keywords: invenio TODO
Platform: any
Classifier: Environment :: Web Environment
Classifier: Intended Audience :: Developers
Classifier: License :: OSI Approved :: GNU General Public License v2 (GPLv2)
Classifier: Operating System :: OS Independent
Classifier: Programming Language :: Python
Classifier: Topic :: Internet :: WWW/HTTP :: Dynamic Content
Classifier: Topic :: Software Development :: Libraries :: Python Modules
Classifier: Programming Language :: Python :: 2
Classifier: Programming Language :: Python :: 2.7
Classifier: Development Status :: 1 - Planning
Requires-Dist: Cerberus (>=0.7,<0.7.1)
Requires-Dist: Flask-Admin (>=1.1.0)
Requires-Dist: Flask-Assets (>=0.10)
Requires-Dist: Flask-Babel (>=0.9)
Requires-Dist: Flask-Breadcrumbs (>=0.2)
Requires-Dist: Flask-Cache (>=0.12)
Requires-Dist: Flask-Collect (>=1.1.1)
Requires-Dist: Flask-Email (>=1.4.4)
Requires-Dist: Flask-Gravatar (>=0.4.2)
Requires-Dist: Flask-IIIF (>=0.2.0)
Requires-Dist: Flask-Login (>=0.2.7)
Requires-Dist: Flask-Menu (>=0.2)
Requires-Dist: Flask-OAuthlib (>=0.6.0,<0.7)
Requires-Dist: Flask-Principal (>=0.4)
Requires-Dist: Flask-RESTful (>=0.2.12)
Requires-Dist: Flask-Registry (>=0.2)
Requires-Dist: Flask-SQLAlchemy (>=2.0)
Requires-Dist: Flask-Script (>=2.0.5)
Requires-Dist: Flask-WTF (>=0.10.2)
Requires-Dist: Flask (>=0.10.1)
Requires-Dist: MySQL-python (>=1.2.5)
Requires-Dist: backports.lzma (>=0.0.3)
Requires-Dist: celery (>=3.1.8)
Requires-Dist: elasticsearch (>=1.3.0)
Requires-Dist: fixture (>=1.5)
Requires-Dist: intbitset (>=2.0.0)
Requires-Dist: invenio-base (>=0.3.1)
Requires-Dist: invenio-celery (>=0.1.1)
Requires-Dist: invenio-utils (>=0.2.0)
Requires-Dist: lxml (>=3.3)
Requires-Dist: oauthlib (==0.7.2)
Requires-Dist: passlib (>=1.6.2)
Requires-Dist: python-dateutil (>=1.5)
Requires-Dist: raven (>=5.0.0)
Requires-Dist: redis (>=2.8.0)
Requires-Dist: requests (>=2.4.0)
Requires-Dist: six (>=1.7.2)
Requires-Dist: sqlalchemy-utils[encrypted] (>=0.31.0)
Provides-Extra: docs
Requires-Dist: Sphinx (>=1.3); extra == 'docs'
Requires-Dist: sphinx-rtd-theme (>=0.1.7); extra == 'docs'
Provides-Extra: tests
Requires-Dist: coverage (>=4.0.0); extra == 'tests'
Requires-Dist: Flask-SSO (>=0.2); extra == 'tests'
Requires-Dist: httpretty (>=0.8.10); extra == 'tests'
Requires-Dist: invenio-access (>=0.2.0); extra == 'tests'
Requires-Dist: invenio-accounts (>=0.2.0); extra == 'tests'
Requires-Dist: invenio-collections (>=0.2.0); extra == 'tests'
Requires-Dist: invenio-records (>=0.3.4.post1); extra == 'tests'
Requires-Dist: invenio-oauth2server (>=0.2.0); extra == 'tests'
Requires-Dist: invenio-testing (>=0.1.1); extra == 'tests'
Requires-Dist: mock (>=1.0.1); extra == 'tests'
Requires-Dist: pytest (>=2.8.0); extra == 'tests'
Requires-Dist: pytest-cov (>=2.1.0); extra == 'tests'
Requires-Dist: pytest-isort (>=0.1.0); extra == 'tests'
Requires-Dist: pytest-pep8 (>=1.0.6); extra == 'tests'
Requires-Dist: setuptools (>=17.1); extra == 'tests'
